recallkit/__init__.py
recallkit/memory_filter.py
recallkit/util/__init__.py
recallkit/util/constants.py
recallkit/util/messages.py
recallkit-0.1.1.dist-info/METADATA
recallkit-0.1.1.dist-info/WHEEL
recallkit-0.1.1.dist-info/entry_points.txt
recallkit-0.1.1.dist-info/top_level.txt
recallkit-0.1.1.dist-info/RECORD
