Metadata-Version: 2.4
Name: recallkit
Version: 0.1.1
Summary: Add your description here
License-Expression: Apache-2.0
Project-URL: Homepage, https://github.com/tombedor/recallkit
Project-URL: Changelog, https://github.com/tombedor/recallkit/releases
Project-URL: Issues, https://github.com/tombedor/recallkit/issues
Project-URL: CI, https://github.com/tombedor/recallkit/actions
Requires-Python: >=3.9
Requires-Dist: litellm
Provides-Extra: test
Requires-Dist: pytest>=7.0.0; extra == "test"
